{
    "title": "Real-Time Motion Planning for Drones",
    "year": "2024",
    "tag": "Motion Planning",
    "description": "Built a real-time 3D motion planning framework for aerial robots operating in unknown and cluttered environments. Integrated OctoMap for global mapping and EDT3D for local collision checking. Implemented a kinodynamic RRT-based planner accounting for vehicle dynamics and obstacle avoidance. Validated collision-free navigation performance in simulation.",
    "image": "https://via.placeholder.com/600x400?text=Motion+Planning",
    "skills": [
        "C++",
        "ROS2",
        "OctoMap",
        "EDT3D"
    ],
    "links": [
        {
            "label": "Source",
            "url": "https://github.com/ShreyasKhobragade/",
            "iconType": "github"
        }
    ]
}